Verification_Assignment/1_rtl/vending_machine.sv
module vending_machine #(
    parameter N = 2, 
    parameter M = 2  
)(
    input  logic        clk,
    input  logic        rst,
    input  logic [31:0] coin_in,     
    input  logic [31:0] button_in,   
    output logic [31:0] change_out,  
    output logic [31:0] beverage_out 
);

    typedef enum {IDLE, DELIVER, CHANGE} state_t;
    state_t current_state;

    logic [31:0] credit;
    logic [31:0] timer;
    logic [31:0] selected_bev; 

    localparam COST_WATER = 30;
    localparam COST_SODA  = 50;
    localparam MIN_COST   = 30; 

    always_ff @(posedge clk or posedge rst) begin
        if (rst) begin
            current_state <= IDLE;
            credit        <= 0;
            timer         <= 0;
            change_out    <= 0;
            beverage_out  <= 0;
            selected_bev  <= 0;
        end else begin
            beverage_out <= 0;
            change_out   <= 0;

            case (current_state)
                IDLE: begin
                    if (coin_in == 10 || coin_in == 20 || coin_in == 50 || 
                        coin_in == 100 || coin_in == 200) begin
                        credit <= credit + coin_in;
                    end

                    if (button_in == 1 && credit >= COST_WATER) begin
                        credit <= credit - COST_WATER;
                        selected_bev <= 1;
                        timer <= N;
                        current_state <= DELIVER;
                    end else if (button_in == 2 && credit >= COST_SODA) begin
                        credit <= credit - COST_SODA;
                        selected_bev <= 2;
                        timer <= N;
                        current_state <= DELIVER;
                    end
                end

                DELIVER: begin
                    if (timer > 0) begin
                        timer <= timer - 1;
                    end else begin
                        beverage_out <= selected_bev; 
                        
                        if (credit < MIN_COST && credit > 0) begin
                            timer <= M;
                            current_state <= CHANGE;
                        end else begin
                            current_state <= IDLE;
                        end
                    end
                end

                CHANGE: begin
                    if (timer > 0) begin
                        timer <= timer - 1;
                    end else begin
                        change_out <= credit; 
                        credit <= 0;
                        current_state <= IDLE;
                    end
                end
            endcase
        end
    end

endmodule

Verification_Assignment/2_simple_tb/simple_tb.sv
`timescale 1ns/1ps

module simple_tb;

    logic clk;
    logic rst;
    logic [31:0] coin_in;
    logic [31:0] button_in;
    logic [31:0] change_out;
    logic [31:0] beverage_out;

    vending_machine #(
        .N(2), 
        .M(2)
    ) dut (
        .clk(clk),
        .rst(rst),
        .coin_in(coin_in),
        .button_in(button_in),
        .change_out(change_out),
        .beverage_out(beverage_out)
    );

    initial begin
        clk = 0;
        forever #5 clk = ~clk;
    end

    initial begin
        rst = 1;
        coin_in = 0;
        button_in = 0;
        
        #20 rst = 0;

        // TC1: Water delivery test
        #10 coin_in = 10;
        #10 coin_in = 0; 
        #10 coin_in = 20;
        #10 coin_in = 0;
        
        #10 button_in = 1;
        #10 button_in = 0;

        #50;

        // TC2: Soda delivery and change test
        #10 coin_in = 50;
        #10 coin_in = 0;
        #10 coin_in = 10;
        #10 coin_in = 0;

        #10 button_in = 2;
        #10 button_in = 0;

        #100;

        $display("Simulation finished");
        $finish;
    end

endmodule

Verification_Assignment/6_traces/simple_tb.vcd
$date
	Wed Feb 11 10:51:54 2026
$end
$version
	QuestaSim Version 2021.3_2
$end
$timescale
	1ps
$end

$scope module simple_tb $end
$var reg 1 ! clk $end
$var reg 1 " rst $end
$var reg 32 # coin_in [31:0] $end
$var reg 32 $ button_in [31:0] $end
$var reg 32 % change_out [31:0] $end
$var reg 32 & beverage_out [31:0] $end

$scope module dut $end
$var parameter 32 ' N $end
$var parameter 32 ( M $end
$var parameter 32 ) COST_WATER $end
$var parameter 32 * COST_SODA $end
$var parameter 32 + MIN_COST $end
$var wire 1 , clk $end
$var wire 1 - rst $end
$var wire 1 . coin_in [31] $end
$var wire 1 / coin_in [30] $end
$var wire 1 0 coin_in [29] $end
$var wire 1 1 coin_in [28] $end
$var wire 1 2 coin_in [27] $end
$var wire 1 3 coin_in [26] $end
$var wire 1 4 coin_in [25] $end
$var wire 1 5 coin_in [24] $end
$var wire 1 6 coin_in [23] $end
$var wire 1 7 coin_in [22] $end
$var wire 1 8 coin_in [21] $end
$var wire 1 9 coin_in [20] $end
$var wire 1 : coin_in [19] $end
$var wire 1 ; coin_in [18] $end
$var wire 1 < coin_in [17] $end
$var wire 1 = coin_in [16] $end
$var wire 1 > coin_in [15] $end
$var wire 1 ? coin_in [14] $end
$var wire 1 @ coin_in [13] $end
$var wire 1 A coin_in [12] $end
$var wire 1 B coin_in [11] $end
$var wire 1 C coin_in [10] $end
$var wire 1 D coin_in [9] $end
$var wire 1 E coin_in [8] $end
$var wire 1 F coin_in [7] $end
$var wire 1 G coin_in [6] $end
$var wire 1 H coin_in [5] $end
$var wire 1 I coin_in [4] $end
$var wire 1 J coin_in [3] $end
$var wire 1 K coin_in [2] $end
$var wire 1 L coin_in [1] $end
$var wire 1 M coin_in [0] $end
$var wire 1 N button_in [31] $end
$var wire 1 O button_in [30] $end
$var wire 1 P button_in [29] $end
$var wire 1 Q button_in [28] $end
$var wire 1 R button_in [27] $end
$var wire 1 S button_in [26] $end
$var wire 1 T button_in [25] $end
$var wire 1 U button_in [24] $end
$var wire 1 V button_in [23] $end
$var wire 1 W button_in [22] $end
$var wire 1 X button_in [21] $end
$var wire 1 Y button_in [20] $end
$var wire 1 Z button_in [19] $end
$var wire 1 [ button_in [18] $end
$var wire 1 \ button_in [17] $end
$var wire 1 ] button_in [16] $end
$var wire 1 ^ button_in [15] $end
$var wire 1 _ button_in [14] $end
$var wire 1 ` button_in [13] $end
$var wire 1 a button_in [12] $end
$var wire 1 b button_in [11] $end
$var wire 1 c button_in [10] $end
$var wire 1 d button_in [9] $end
$var wire 1 e button_in [8] $end
$var wire 1 f button_in [7] $end
$var wire 1 g button_in [6] $end
$var wire 1 h button_in [5] $end
$var wire 1 i button_in [4] $end
$var wire 1 j button_in [3] $end
$var wire 1 k button_in [2] $end
$var wire 1 l button_in [1] $end
$var wire 1 m button_in [0] $end
$var reg 32 n change_out [31:0] $end
$var reg 32 o beverage_out [31:0] $end
$var integer 32 p current_state $end
$var reg 32 q credit [31:0] $end
$var reg 32 r timer [31:0] $end
$var reg 32 s selected_bev [31:0] $end
$upscope $end
$upscope $end
$enddefinitions $end
#0
$dumpvars
0!
1"
b0 #
b0 $
b0 %
b0 &
b0 n
b0 o
b0 q
b0 r
b0 s
b10 '
b10 (
b11110 )
b110010 *
b11110 +
b0 p
0,
1-
0M
0L
0K
0J
0I
0H
0G
0F
0E
0D
0C
0B
0A
0@
0?
0>
0=
0<
0;
0:
09
08
07
06
05
04
03
02
01
00
0/
0.
0m
0l
0k
0j
0i
0h
0g
0f
0e
0d
0c
0b
0a
0`
0_
0^
0]
0\
0[
0Z
0Y
0X
0W
0V
0U
0T
0S
0R
0Q
0P
0O
0N
$end
#5000
1!
1,
#10000
0!
0,
#15000
1!
1,
#20000
0"
0!
0-
0,
#25000
1!
1,
#30000
b1010 #
0!
1L
1J
0,
#35000
1!
1,
b1010 q
#40000
b0 #
0!
0L
0J
0,
#45000
1!
1,
#50000
b10100 #
0!
1K
1I
0,
#55000
1!
1,
b11110 q
#60000
b0 #
0!
0K
0I
0,
#65000
1!
1,
#70000
b1 $
0!
1m
0,
#75000
1!
1,
b0 q
b1 s
b10 r
b1 p
#80000
b0 $
0!
0m
0,
#85000
1!
1,
b1 r
#90000
0!
0,
#95000
1!
1,
b0 r
#100000
0!
0,
#105000
1!
1,
b1 o
b0 p
b1 &
#110000
0!
0,
#115000
1!
1,
b0 o
b0 &
#120000
0!
0,
#125000
1!
1,
#130000
0!
0,
#135000
1!
1,
#140000
b110010 #
0!
1L
1I
1H
0,
#145000
1!
1,
b110010 q
#150000
b0 #
0!
0L
0I
0H
0,
#155000
1!
1,
#160000
b1010 #
0!
1L
1J
0,
#165000
1!
1,
b111100 q
#170000
b0 #
0!
0L
0J
0,
#175000
1!
1,
#180000
b10 $
0!
1l
0,
#185000
1!
1,
b1010 q
b10 s
b10 r
b1 p
#190000
b0 $
0!
0l
0,
#195000
1!
1,
b1 r
#200000
0!
0,
#205000
1!
1,
b0 r
#210000
0!
0,
#215000
1!
1,
b10 o
b10 r
b10 p
b10 &
#220000
0!
0,
#225000
1!
1,
b0 o
b1 r
b0 &
#230000
0!
0,
#235000
1!
1,
b0 r
#240000
0!
0,
#245000
1!
1,
b1010 n
b0 q
b0 p
b1010 %
#250000
0!
0,
#255000
1!
1,
b0 n
b0 %
